Metadata-Version: 2.1
Name: myOOP
Version: 0.0
Summary: A library that includes class utilities.
Home-page: https://github.com/Eric-fuyc/myOOP
Author: Yuchen FU
Author-email: 
Classifier: Development Status :: 4 - Beta
Classifier: Programming Language :: Python :: 3.6
Classifier: Programming Language :: Python :: 3.7
Classifier: Programming Language :: Python :: 3.8
Classifier: Programming Language :: Python :: 3.9
Classifier: Programming Language :: Python :: 3.10
Classifier: Intended Audience :: Developers
Classifier: License :: OSI Approved :: Apache Software License
Classifier: Operating System :: OS Independent
Requires-Python: >=3.6
